odoo/addons/auth_api_key/README.rst
odoo/addons/auth_api_key/__init__.py
odoo/addons/auth_api_key/__manifest__.py
odoo/addons/auth_api_key/i18n/auth_api_key.pot
odoo/addons/auth_api_key/migrations/12.0.2.0.0/post-migrate.py
odoo/addons/auth_api_key/models/__init__.py
odoo/addons/auth_api_key/models/auth_api_key.py
odoo/addons/auth_api_key/models/ir_http.py
odoo/addons/auth_api_key/readme/CONFIGURE.rst
odoo/addons/auth_api_key/readme/CONTRIBUTORS.rst
odoo/addons/auth_api_key/readme/DESCRIPTION.rst
odoo/addons/auth_api_key/readme/USAGE.rst
odoo/addons/auth_api_key/security/ir.model.access.csv
odoo/addons/auth_api_key/static/description/icon.png
odoo/addons/auth_api_key/static/description/index.html
odoo/addons/auth_api_key/tests/__init__.py
odoo/addons/auth_api_key/tests/test_auth_api_key.py
odoo/addons/auth_api_key/views/auth_api_key.xml
odoo13_addon_auth_api_key-13.0.1.1.1.dist-info/METADATA
odoo13_addon_auth_api_key-13.0.1.1.1.dist-info/WHEEL
odoo13_addon_auth_api_key-13.0.1.1.1.dist-info/top_level.txt
odoo13_addon_auth_api_key-13.0.1.1.1.dist-info/RECORD
